src/__init__.py
src/catalog_manager.py
src/starteller_cli.py
starteller_cli-1.2.1.dist-info/licenses/LICENSE
starteller_cli-1.2.1.dist-info/licenses/NOTICE
starteller_cli-1.2.1.dist-info/METADATA
starteller_cli-1.2.1.dist-info/WHEEL
starteller_cli-1.2.1.dist-info/entry_points.txt
starteller_cli-1.2.1.dist-info/top_level.txt
starteller_cli-1.2.1.dist-info/RECORD
