Metadata-Version: 2.4
Name: starteller-cli
Version: 1.2.1
Summary: A command-line tool for astrophotographers to find optimal viewing times for deep sky objects
Author: ConnRaus
License: AGPL-3.0-or-later
Project-URL: Homepage, https://github.com/ConnRaus/StarTeller-CLI
Project-URL: Repository, https://github.com/ConnRaus/StarTeller-CLI
Keywords: astronomy,astrophotography,telescope,deep-sky-objects,ngc,messier,observing,astronomical-calculations
Classifier: Development Status :: 4 - Beta
Classifier: Intended Audience :: Science/Research
Classifier: Topic :: Scientific/Engineering :: Astronomy
Classifier: Programming Language :: Python :: 3
Classifier: Programming Language :: Python :: 3.8
Classifier: Programming Language :: Python :: 3.9
Classifier: Programming Language :: Python :: 3.10
Classifier: Programming Language :: Python :: 3.11
Classifier: Programming Language :: Python :: 3.12
Requires-Python: >=3.8
License-File: LICENSE
License-File: NOTICE
Requires-Dist: pandas>=1.5.0
Requires-Dist: numpy>=1.21.0
Requires-Dist: pytz>=2022.1
Requires-Dist: timezonefinder>=6.0.0
Requires-Dist: tqdm>=4.60.0
Dynamic: license-file
